dungeon_eos/DungeonAlgorithm.py
dungeon_eos/RandomGen.py
dungeon_eos/__init__.py
dungeon_eos/example.py
dungeon_eos-0.0.4.dist-info/LICENSE
dungeon_eos-0.0.4.dist-info/METADATA
dungeon_eos-0.0.4.dist-info/WHEEL
dungeon_eos-0.0.4.dist-info/top_level.txt
dungeon_eos-0.0.4.dist-info/RECORD
