Metadata-Version: 2.1
Name: dungeon-eos
Version: 0.0.4
Summary: A package that simulates PMD EoS dungeon generation. 
Home-page: https://github.com/irdkwia/dungeon_eos/
Author: irdkwia idkmn
Author-email: irdkwia2000@gmail.com
License: UNKNOWN
Keywords: Dungeon,PMD,Explorers,Generator
Platform: UNKNOWN
Classifier: Development Status :: 3 - Alpha
Classifier: Intended Audience :: Developers
Classifier: License :: OSI Approved :: GNU General Public License v3 or later (GPLv3+)
Classifier: Programming Language :: Python :: 3
Classifier: Programming Language :: Python :: 3.4
Classifier: Programming Language :: Python :: 3.5
Classifier: Programming Language :: Python :: 3.6
Classifier: Programming Language :: Python :: 3.7
Classifier: Programming Language :: Python :: 3.8
Classifier: Programming Language :: Python :: 3.9
License-File: LICENSE
